cythondfprint/LICENSE
cythondfprint/README.MD
cythondfprint/__init__.py
cythondfprint/cythonprinter.pyx
cythondfprint/cythonprintercompile.py
cythondfprint/requirements.txt
cythondfprint/thirdparty.json
cythondfprint-0.13.dist-info/LICENSE.rst
cythondfprint-0.13.dist-info/METADATA
cythondfprint-0.13.dist-info/WHEEL
cythondfprint-0.13.dist-info/top_level.txt
cythondfprint-0.13.dist-info/RECORD
